rigidanalytics_tracker/__init__.py
rigidanalytics_tracker/_compat.py
rigidanalytics_tracker/_types.py
rigidanalytics_tracker/apps.py
rigidanalytics_tracker/middleware.py
rigidanalytics_tracker/tracker.py
rigidanalytics_tracker/transport.py
rigidanalytics_tracker/worker.py
rigidanalytics_tracker/django/__init__.py
rigidanalytics_tracker/django/tracker.py
rigidanalytics_tracker/flask/__init__.py
rigidanalytics_tracker/flask/tracker.py
tests/__init__.py
tests/banner_django.py
tests/banner_flask.py
tests/test_django_integration.py
tests/test_flask_integration.py
tests/test_django_app/__init__.py
tests/test_django_app/settings.py
tests/test_django_app/urls.py
tests/test_django_app/views.py
rigidanalytics_tracker-2.0.5.dist-info/LICENSE
rigidanalytics_tracker-2.0.5.dist-info/METADATA
rigidanalytics_tracker-2.0.5.dist-info/WHEEL
rigidanalytics_tracker-2.0.5.dist-info/top_level.txt
rigidanalytics_tracker-2.0.5.dist-info/RECORD
