Metadata-Version: 2.1
Name: rigidanalytics-tracker
Version: 2.0.5
Summary: Server-side analytics
Home-page: https://github.com/reustleco/rigidanalytics-tracker/
Author: Shane Reustle
Author-email: shane@reustle.co
License: MIT
Platform: UNKNOWN
Requires-Dist: blinker
Requires-Dist: urllib3
